seligimus/__init__.py
seligimus/exception.py
seligimus/py.typed
seligimus/characters/__init__.py
seligimus/characters/digits.py
seligimus/characters/letters.py
seligimus/characters/lowercase_letters.py
seligimus/characters/symbols.py
seligimus/characters/uppercase_letters.py
seligimus/exceptions/__init__.py
seligimus/exceptions/iteration/__init__.py
seligimus/exceptions/iteration/no_head.py
seligimus/iteration/__init__.py
seligimus/iteration/head.py
seligimus/iteration/index.py
seligimus/maths/__init__.py
seligimus/maths/integer_position_2d.py
seligimus/maths/integer_size_2d.py
seligimus/maths/vector_2.py
seligimus/python/__init__.py
seligimus/python/classes/__init__.py
seligimus/python/classes/attributes.py
seligimus/python/classes/empty_class.py
seligimus/python/classes/is_subclass_of_generic.py
seligimus/python/decorators/__init__.py
seligimus/python/decorators/standard_representation.py
seligimus/python/decorators/operators/__init__.py
seligimus/python/decorators/operators/equality/__init__.py
seligimus/python/decorators/operators/equality/equal_instance_attributes.py
seligimus/python/decorators/operators/equality/equal_type.py
seligimus/python/decorators/operators/equality/equality_operator.py
seligimus/python/decorators/operators/equality/standard_equality.py
seligimus/python/functions/__init__.py
seligimus/python/functions/parameter_kind.py
seligimus/python/functions/parameter_list.py
seligimus/python/functions/parameters.py
seligimus/standards/__init__.py
seligimus/standards/ansi/__init__.py
seligimus/standards/ansi/escape_codes/__init__.py
seligimus/standards/ansi/escape_codes/color.py
seligimus/standards/ansi/escape_codes/control.py
seligimus/standards/ansi/escape_codes/cursor.py
seligimus/standards/ansi/escape_codes/erase.py
seligimus/standards/ansi/escape_codes/screen.py
seligimus/strings/__init__.py
seligimus/strings/drop.py
seligimus/strings/join.py
seligimus/strings/distance/__init__.py
seligimus/strings/distance/levenshtein_distance.py
seligimus-0.19.0.dist-info/LICENSE.txt
seligimus-0.19.0.dist-info/METADATA
seligimus-0.19.0.dist-info/WHEEL
seligimus-0.19.0.dist-info/top_level.txt
seligimus-0.19.0.dist-info/RECORD
