Metadata-Version: 2.1
Name: seligimus
Version: 0.19.0
Summary: A mono-library.
Home-page: https://github.com/AustinScola/seligimus
Author: Austin Scola
Author-email: austinscola@gmail.com
License: UNKNOWN
Platform: UNKNOWN
Classifier: Development Status :: 2 - Pre-Alpha
Classifier: Programming Language :: Python :: 3
Classifier: License :: OSI Approved :: MIT License
Classifier: Operating System :: OS Independent
Classifier: Topic :: Software Development :: Libraries
Classifier: Typing :: Typed
Requires-Python: >=3.6
